{"expireTime":9007200905916873000,"key":"ref-c52d0e3c-42d7-5467-a981-2570d3a76cf8","val":{"1400286598":{"contentDigest":"9b8c248bcabe302afd8a71fd42b0d0fb","args":{"width":1906,"placeholder":"blurred","layout":"fullWidth","formats":["auto","webp"],"breakpoints":[750,1080,1366,1920]},"cacheFilename":"D:\\Projekty\\amadeo-media\\.cache\\caches\\gatsby-plugin-image\\1400286598.json"},"2559761055":{"contentDigest":"86ffd990b3593f91a8eb7ef9c6c88c24","args":{"width":363,"placeholder":"blurred","layout":"constrained"},"cacheFilename":"D:\\Projekty\\amadeo-media\\.cache\\caches\\gatsby-plugin-image\\2559761055.json"},"2828708924":{"contentDigest":"9b8c248bcabe302afd8a71fd42b0d0fb","args":{"width":363,"placeholder":"blurred","layout":"fixed","formats":["auto","webp"]},"cacheFilename":"D:\\Projekty\\amadeo-media\\.cache\\caches\\gatsby-plugin-image\\2828708924.json"}}}