{"expireTime":9007200905912527000,"key":"26dcba8bc04b89ec50823e477d90e5b8","val":{"name":"IMAGE_PROCESSING","inputPaths":["D:/Projekty/amadeo-media/src/images/chiara-shop-ss.png"],"outputDir":"D:/Projekty/amadeo-media/public/static/79dc03c657975ff692cd91f434aa13c3","args":{"isLazy":false,"operations":[{"outputPath":"2e7af\\chiara-shop-ss.png","args":{"height":673,"width":750,"cropFocus":17,"toFormat":"png","fit":"cover"}},{"outputPath":"7c150\\chiara-shop-ss.png","args":{"height":969,"width":1080,"cropFocus":17,"toFormat":"png","fit":"cover"}}],"pluginOptions":{"base64Width":20,"forceBase64Format":"","useMozJpeg":false,"stripMetadata":true,"lazyImageGeneration":true,"defaultQuality":50,"failOnError":true,"plugins":[]}}}}