{"expireTime":9007200905905161000,"key":"913a6be47f6b90a7900cf4ddf68bcb8f","val":{"name":"IMAGE_PROCESSING","inputPaths":["D:/Projekty/amadeo-media/src/images/secretpleasure-logo.svg"],"outputDir":"D:/Projekty/amadeo-media/public/static/eec119cbcec5e34f3c74ed98c3bea6dc","args":{"isLazy":false,"operations":[{"outputPath":"65086\\secretpleasure-logo.webp","args":{"height":23,"width":23,"cropFocus":17,"toFormat":"webp","fit":"cover"}},{"outputPath":"29677\\secretpleasure-logo.webp","args":{"height":45,"width":45,"cropFocus":17,"toFormat":"webp","fit":"cover"}}],"pluginOptions":{"base64Width":20,"forceBase64Format":"","useMozJpeg":false,"stripMetadata":true,"lazyImageGeneration":true,"defaultQuality":50,"failOnError":true,"plugins":[]}}}}